setup.py
dm/__init__.py
dm.zopepatches.ztutils.egg-info/PKG-INFO
dm.zopepatches.ztutils.egg-info/SOURCES.txt
dm.zopepatches.ztutils.egg-info/dependency_links.txt
dm.zopepatches.ztutils.egg-info/namespace_packages.txt
dm.zopepatches.ztutils.egg-info/not-zip-safe
dm.zopepatches.ztutils.egg-info/requires.txt
dm.zopepatches.ztutils.egg-info/top_level.txt
dm/zopepatches/__init__.py
dm/zopepatches/ztutils/README.txt
dm/zopepatches/ztutils/VERSION.txt
dm/zopepatches/ztutils/__init__.py
dm/zopepatches/ztutils/tests.py