Metadata-Version: 1.1
Name: dm.zopepatches.ztutils
Version: 2.0
Summary: Patches for Zope's ZTUtils in order to make 'make_query' and 'make_hidden_input* more flexible and more reliable.
Home-page: http://pypi.python.org/pypi/dm.zopepatches.ztutils
Author: Dieter Maurer
Author-email: dieter@handshake.de
License: BSD
Keywords: application development menu web
Platform: UNKNOWN
Classifier: Development Status :: 5 - Production/Stable
Classifier: Intended Audience :: Developers
Classifier: License :: OSI Approved :: Zope Public License
Classifier: Framework :: Zope2
Classifier: Framework :: Zope
Classifier: Framework :: Zope :: 4
Classifier: Operating System :: OS Independent
Classifier: Programming Language :: Python
Classifier: Programming Language :: Python :: 2.7
Classifier: Programming Language :: Python :: 3
Classifier: Topic :: Utilities
